<?xml version="1.0" encoding="UTF-8"?>
<objects serializationModel="Studio.02.02.00">
	<object class="Workspace" id="{90b8a765-8d04-4065-9fac-2a4def819aef}">
		<relationship name="projectSettings">
			<destination>{18904d82-3e92-4774-a5db-fb7a59baa3d0}</destination>
		</relationship>
		<relationship name="changelist">
			<destination>{d2660146-08bb-4679-9bc8-f11e5a3c55b4}</destination>
		</relationship>
	</object>
	<object class="ProjectSettings" id="{18904d82-3e92-4774-a5db-fb7a59baa3d0}">
		<relationship name="activePlatform">
			<destination>{a7ac1750-f55c-44d8-ae4c-7b26cf662a6e}</destination>
		</relationship>
	</object>
	<object class="WorkspaceChangelist" id="{d2660146-08bb-4679-9bc8-f11e5a3c55b4}" />
</objects>
